sndbox/__init__.py
sndbox/sndboxapi.py
sndboxapi-3.0.dist-info/LICENSE
sndboxapi-3.0.dist-info/METADATA
sndboxapi-3.0.dist-info/WHEEL
sndboxapi-3.0.dist-info/top_level.txt
sndboxapi-3.0.dist-info/RECORD
