Metadata-Version: 2.1
Name: sndboxapi
Version: 3.0
Summary: A Python Wrapper for the SNDBOX Rest API
Home-page: https://github.com/PR3R00T/SNDBOX-LIGHT-API
Author: PR3R00T
Author-email: PR3R00T@protonmail.com
License: UNKNOWN
Platform: UNKNOWN
Classifier: Programming Language :: Python :: 3
Classifier: License :: OSI Approved :: MIT License
Classifier: Operating System :: OS Independent
